{
  "opinions": [
    {
      "id": 1781416578313,
      "votes": 0,
      "userName": "Alpha",
      "title": "Life Sucks",
      "body": "Humans spcies living in this world itself a hell"
    },
    {
      "id": 1781416073797,
      "votes": 0,
      "userName": "Vimal",
      "title": "Hitler the great",
      "body": "Hitler war right"
    },
    {
      "id": 1,
      "userName": "Maximilian Schwarzmüller",
      "title": "Do yourself a favor and learn React!",
      "body": "React is an amazing JavaScript library!\n\nDespite all it's shortcomings.",
      "votes": 0
    },
    {
      "id": 2,
      "userName": "Maximilian Schwarzmüller",
      "title": "React has more depth than you might first think!",
      "body": "React is a great library to learn, but it's not just about the basics. Dive deeper!\nFor example with this course!",
      "votes": 0
    }
  ]
}